[
  {
    "id": "1756123485512",
    "name": "Test",
    "description": "test",
    "genre": "test",
    "completed": false,
    "createdAt": "2025-08-25T12:04:45.512Z",
    "updatedAt": "2025-08-25T12:04:45.512Z",
    "issues": {
      "bug": [],
      "controls": [
        {
          "id": "1756123508143",
          "title": "Movement issue",
          "description": "test",
          "category": "controls",
          "priority": "low",
          "urgency": "high",
          "assignee": "1756123446705",
          "status": "open",
          "createdAt": "2025-08-25T12:05:08.143Z",
          "updatedAt": "2025-08-25T12:05:08.143Z"
        }
      ],
      "quest": [],
      "review": []
    }
  }
]